Tool.py
testLib/__init__.py
testLib/bao.py
chengtestLib-1.0.0.dist-info/LICENSE.txt
chengtestLib-1.0.0.dist-info/METADATA
chengtestLib-1.0.0.dist-info/WHEEL
chengtestLib-1.0.0.dist-info/top_level.txt
chengtestLib-1.0.0.dist-info/RECORD
