Metadata-Version: 2.1
Name: chengtestLib
Version: 1.0.0
Summary: this is a testLib
Author: spiderman
Author-email: xxx@163.com
License-File: LICENSE.txt
